LICENSE
MANIFEST.in
README.md
setup.py
hstore_field/__init__.py
hstore_field/fields.py
hstore_field/forms.py
hstore_field/query.py
hstore_field_caseinsensitive.egg-info/PKG-INFO
hstore_field_caseinsensitive.egg-info/SOURCES.txt
hstore_field_caseinsensitive.egg-info/dependency_links.txt
hstore_field_caseinsensitive.egg-info/top_level.txt