Metadata-Version: 1.0
Name: hstore-field-caseinsensitive
Version: 1.0.2
Summary: Support for PostgreSQL's hstore for Django.
Home-page: git@github.com:anantasty/hstore-field.git
Author: Eric Russell
Author-email: eric-r@pobox.com
License: BSD
Platform: UNKNOWN
